ialab/__init__.py
ialab/input/__init__.py
ialab/input/image.py
ialab/pipeline/__init__.py
ialab/pipeline/detection.py
ialab/pipeline/faces.py
ialab/pipeline/model.py
ialab/pipeline/output.py
text/__init__.py
text/model.py
ialab_core-0.2.5.dist-info/LICENSE
ialab_core-0.2.5.dist-info/METADATA
ialab_core-0.2.5.dist-info/WHEEL
ialab_core-0.2.5.dist-info/top_level.txt
ialab_core-0.2.5.dist-info/RECORD
