Metadata-Version: 2.1
Name: ialab-core
Version: 0.2.5
Summary: A utility to help you in your IA projects
Home-page: https://github.com/hselvaggi/ialab-core
Author: Harold Selvaggi
Author-email: harold.selvaggi@gmail.com
License: UNKNOWN
Platform: UNKNOWN
Classifier: Programming Language :: Python :: 3
Classifier: Operating System :: OS Independent
Classifier: Topic :: Scientific/Engineering :: Artificial Intelligence
Requires-Dist: numpy
Requires-Dist: face-recognition
Requires-Dist: opencv-python
